kiota_http/__init__.py
kiota_http/_exceptions.py
kiota_http/_version.py
kiota_http/httpx_request_adapter.py
kiota_http/kiota_client_factory.py
kiota_http/middleware/__init__.py
kiota_http/middleware/async_kiota_transport.py
kiota_http/middleware/headers_inspection_handler.py
kiota_http/middleware/middleware.py
kiota_http/middleware/options/__init__.py
kiota_http/middleware/options/headers_inspection_handler_option.py
kiota_http/middleware/options/parameters_name_decoding_handler_option.py
kiota_http/middleware/options/redirect_handler_option.py
kiota_http/middleware/options/response_handler_option.py
kiota_http/middleware/options/retry_handler_option.py
kiota_http/middleware/options/telemetry_handler_option.py
kiota_http/middleware/options/url_replace_option.py
kiota_http/middleware/options/user_agent_handler_option.py
kiota_http/middleware/parameters_name_decoding_handler.py
kiota_http/middleware/redirect_handler.py
kiota_http/middleware/retry_handler.py
kiota_http/middleware/url_replace_handler.py
kiota_http/middleware/user_agent_handler.py
kiota_http/observability_options.py
kiota_http/py.typed
microsoft_kiota_http-1.9.1.dist-info/LICENSE
microsoft_kiota_http-1.9.1.dist-info/METADATA
microsoft_kiota_http-1.9.1.dist-info/WHEEL
microsoft_kiota_http-1.9.1.dist-info/RECORD
